{
  "fetched_at": "2026-06-27T19:19:03",
  "eth_usd": 1591.53,
  "otherdeed": {
    "collection": {
      "floor_eth": null,
      "volume_eth": null,
      "num_owners": null,
      "listed": null
    },
    "raw_traits": {},
    "resource_floors": {},
    "sales_traits": {},
    "resource_sales": {}
  },
  "expanded": {
    "collection": {
      "floor_eth": 0.083935,
      "volume_eth": 18463.60445885852,
      "num_owners": 12107,
      "listed": null
    },
    "raw_traits": {},
    "resource_floors": {},
    "sales_traits": {},
    "resource_sales": {}
  }
}