{
  "fetched_at": "2026-07-05T13:36:39",
  "eth_usd": 1761.77,
  "otherdeed": {
    "collection": {
      "floor_eth": 0.0888046699,
      "volume_eth": 606306.8672584761,
      "num_owners": 13985,
      "listed": null
    },
    "raw_traits": {},
    "resource_floors": {},
    "sales_traits": {},
    "resource_sales": {}
  },
  "expanded": {
    "collection": {
      "floor_eth": 0.08579997,
      "volume_eth": 18470.45304360132,
      "num_owners": 12103,
      "listed": null
    },
    "raw_traits": {},
    "resource_floors": {},
    "sales_traits": {},
    "resource_sales": {}
  }
}